BytesViewFCM/BytesViewNotificationClient.py
BytesViewFCM/FCMClient.py
BytesViewFCM/NotificationTracker.py
BytesViewFCM/OneSignalClient.py
BytesViewFCM/__init__.py
BytesViewFCM/logger.py
BytesViewFCM/notification_exception.py
BytesViewFCM/utils.py
tests/__init__.py
tests/test_notification.py
bytesviewnotifiactionclient-1.1.6.dist-info/METADATA
bytesviewnotifiactionclient-1.1.6.dist-info/WHEEL
bytesviewnotifiactionclient-1.1.6.dist-info/top_level.txt
bytesviewnotifiactionclient-1.1.6.dist-info/RECORD
