Metadata-Version: 2.1
Name: bytesviewnotifiactionclient
Version: 1.1.6
Summary: A plugin for Notification
Home-page: https://github.com/bytesview/bytesview-notifiaction-client
Author: BytesView
Author-email: contact@bytesview.com
License: UNKNOWN
Keywords: bytesview notification,bytesview notification client
Platform: UNKNOWN
Classifier: Programming Language :: Python :: 3
Classifier: License :: OSI Approved :: MIT License
Classifier: Operating System :: OS Independent
Requires-Python: >=3.6
Requires-Dist: firebase-admin
Requires-Dist: rq
Requires-Dist: redis
Requires-Dist: onesignal-python-api
Requires-Dist: mysql-connector-python
